mcdplib/__init__.py
mcdplib/core/__init__.py
mcdplib/core/evaluation.py
mcdplib/core/file.py
mcdplib/core/identifier.py
mcdplib/core/pack.py
mcdplib/core/registry.py
mcdplib/core/string.py
mcdplib/core/text.py
mcdplib/core/resource/__init__.py
mcdplib/core/resource/resource.py
mcdplib/core/resource/resource_binary.py
mcdplib/core/resource/resource_object.py
mcdplib/core/resource/resource_string.py
mcdplib/datapack/__init__.py
mcdplib/datapack/datapack.py
mcdplib/datapack/function.py
mcdplib/datapack/function_template.py
mcdplib/resourcepack/__init__.py
mcdplib/resourcepack/resourcepack.py
mcdplib/resourcepack/shader.py
mcdplib-0.4.0.dist-info/licenses/LICENSE
mcdplib-0.4.0.dist-info/METADATA
mcdplib-0.4.0.dist-info/WHEEL
mcdplib-0.4.0.dist-info/top_level.txt
mcdplib-0.4.0.dist-info/RECORD
