Metadata-Version: 2.4
Name: mcdplib
Version: 0.4.0
Summary: Инструмент для генерации датапаков
Author-email: Vladislav117 <siluetkysta@gmail.com>
Project-URL: Homepage, https://github.com/Vladislav117/mcdplib
Project-URL: Issues, https://github.com/Vladislav117/mcdplib/issues
Classifier: Programming Language :: Python :: 3
Classifier: License :: OSI Approved :: MIT License
Classifier: Operating System :: OS Independent
Requires-Python: >=3.9
License-File: LICENSE
Dynamic: license-file
